nlp_primitives/__init__.py
nlp_primitives/conftest.py
nlp_primitives/diversity_score.py
nlp_primitives/lsa.py
nlp_primitives/mean_characters_per_sentence.py
nlp_primitives/number_of_sentences.py
nlp_primitives/part_of_speech_count.py
nlp_primitives/polarity_score.py
nlp_primitives/stopword_count.py
nlp_primitives/utilities.py
nlp_primitives/version.py
nlp_primitives/data/nltk-data/corpora/gutenberg/austen-emma.txt
nlp_primitives/data/nltk-data/corpora/gutenberg/austen-persuasion.txt
nlp_primitives/data/nltk-data/corpora/gutenberg/austen-sense.txt
nlp_primitives/data/nltk-data/corpora/gutenberg/bible-kjv.txt
nlp_primitives/data/nltk-data/corpora/gutenberg/blake-poems.txt
nlp_primitives/data/nltk-data/corpora/gutenberg/bryant-stories.txt
nlp_primitives/data/nltk-data/corpora/gutenberg/burgess-busterbrown.txt
nlp_primitives/data/nltk-data/corpora/gutenberg/carroll-alice.txt
nlp_primitives/data/nltk-data/corpora/gutenberg/chesterton-ball.txt
nlp_primitives/data/nltk-data/corpora/gutenberg/chesterton-brown.txt
nlp_primitives/data/nltk-data/corpora/gutenberg/chesterton-thursday.txt
nlp_primitives/data/nltk-data/corpora/gutenberg/edgeworth-parents.txt
nlp_primitives/data/nltk-data/corpora/gutenberg/melville-moby_dick.txt
nlp_primitives/data/nltk-data/corpora/gutenberg/milton-paradise.txt
nlp_primitives/data/nltk-data/corpora/gutenberg/shakespeare-caesar.txt
nlp_primitives/data/nltk-data/corpora/gutenberg/shakespeare-hamlet.txt
nlp_primitives/data/nltk-data/corpora/gutenberg/shakespeare-macbeth.txt
nlp_primitives/data/nltk-data/corpora/gutenberg/whitman-leaves.txt
nlp_primitives/data/nltk-data/corpora/omw-1.4/README
nlp_primitives/data/nltk-data/corpora/omw-1.4/citation.bib
nlp_primitives/data/nltk-data/corpora/omw-1.4/als/LICENSE
nlp_primitives/data/nltk-data/corpora/omw-1.4/als/README
nlp_primitives/data/nltk-data/corpora/omw-1.4/als/citation.bib
nlp_primitives/data/nltk-data/corpora/omw-1.4/als/wn-data-als.tab
nlp_primitives/data/nltk-data/corpora/omw-1.4/arb/LICENSE
nlp_primitives-2.13.0.dist-info/LICENSE
nlp_primitives-2.13.0.dist-info/METADATA
nlp_primitives-2.13.0.dist-info/WHEEL
nlp_primitives-2.13.0.dist-info/entry_points.txt
nlp_primitives-2.13.0.dist-info/top_level.txt
nlp_primitives-2.13.0.dist-info/RECORD
